python_dd/dd.py
python_dd-0.0.15.dist-info/METADATA
python_dd-0.0.15.dist-info/WHEEL
python_dd-0.0.15.dist-info/top_level.txt
python_dd-0.0.15.dist-info/RECORD
